trackthenews/__init__.py
trackthenews/base_blocklist.py
trackthenews/core.py
trackthenews/fonts/LICENSE_OFL.txt
trackthenews/fonts/NotoSerif-Regular.ttf
trackthenews-0.4.dist-info/LICENSE
trackthenews-0.4.dist-info/METADATA
trackthenews-0.4.dist-info/WHEEL
trackthenews-0.4.dist-info/entry_points.txt
trackthenews-0.4.dist-info/RECORD
