Metadata-Version: 2.1
Name: trackthenews
Version: 0.4
Summary: Monitor RSS feeds for keywords and act on matching results. A special project of the Freedom of the Press Foundation.
Home-page: https://github.com/freedomofpress/trackthenews
License: MIT
Author: Freedom of the Press Foundation
Author-email: info@freedom.press
Maintainer: Harris Lapiroff
Maintainer-email: harris@freedom.press
Requires-Python: >=3.11,<3.12
Classifier: License :: OSI Approved :: MIT License
Classifier: Programming Language :: Python :: 3
Classifier: Programming Language :: Python :: 3.11
Requires-Dist: Mastodon.py (>=1.8.1,<2.0.0)
Requires-Dist: Pillow (>=10.0.0,<11.0.0)
Requires-Dist: beautifulsoup4 (>=4.12.3,<5.0.0)
Requires-Dist: feedparser (>=6.0,<7.0)
Requires-Dist: future (>=0.17.1,<0.18.0)
Requires-Dist: html2text (==2018.1.9)
Requires-Dist: lxml[html-clean] (>=5.3.0,<6.0.0)
Requires-Dist: pyaml (>=18.11.0,<19.0.0)
Requires-Dist: readability-lxml (>=0.8.1,<0.9.0)
Requires-Dist: requests (>=2.31.0,<3.0.0)
Requires-Dist: tweepy (>=4.14.0,<5.0.0)
Project-URL: Repository, https://github.com/freedomofpress/trackthenews
